alma_cdk/aws_interface_endpoints/__init__.py
alma_cdk/aws_interface_endpoints/py.typed
alma_cdk/aws_interface_endpoints/_jsii/__init__.py
alma_cdk/aws_interface_endpoints/_jsii/aws-interface-endpoints@0.0.6.jsii.tgz
alma_cdk.aws_interface_endpoints-0.0.6.dist-info/LICENSE
alma_cdk.aws_interface_endpoints-0.0.6.dist-info/METADATA
alma_cdk.aws_interface_endpoints-0.0.6.dist-info/WHEEL
alma_cdk.aws_interface_endpoints-0.0.6.dist-info/top_level.txt
alma_cdk.aws_interface_endpoints-0.0.6.dist-info/RECORD
